pyMicroeconomics/__init__.py
pyMicroeconomics/core/__init__.py
pyMicroeconomics/core/equation_types.py
pyMicroeconomics/core/market_base.py
pyMicroeconomics/core/symbols.py
pyMicroeconomics/market/__init__.py
pyMicroeconomics/market/demand.py
pyMicroeconomics/market/supply.py
pyMicroeconomics/market/equilibrium/__init__.py
pyMicroeconomics/market/equilibrium/main.py
pyMicroeconomics/market/equilibrium/solver.py
pyMicroeconomics/market/equilibrium/surplus.py
pyMicroeconomics/market/equilibrium/types.py
pyMicroeconomics/market/equilibrium/validation.py
pyMicroeconomics/optimization/optimization.py
pyMicroeconomics/visualization/__init__.py
pyMicroeconomics/visualization/display.py
pyMicroeconomics/visualization/plotting.py
pymicroeconomics-0.0.6.dist-info/WHEEL
pymicroeconomics-0.0.6.dist-info/METADATA
pymicroeconomics-0.0.6.dist-info/RECORD
